tgan/__init__.py
tgan/cli.py
tgan/data.py
tgan/model.py
tgan/trainer.py
tgan/research/__init__.py
tgan/research/evaluation.py
tgan/research/experiments.py
tgan-0.1.0.dist-info/AUTHORS.rst
tgan-0.1.0.dist-info/LICENSE
tgan-0.1.0.dist-info/METADATA
tgan-0.1.0.dist-info/WHEEL
tgan-0.1.0.dist-info/entry_points.txt
tgan-0.1.0.dist-info/top_level.txt
tgan-0.1.0.dist-info/RECORD
